fphysics/constants.py
fphysics/math_concepts.py
fphysics/physics_concepts.py
fphysics/applications/__init__.py
fphysics/applications/energy.py
fphysics/applications/engineering.py
fphysics/applications/environmental.py
fphysics/applications/medical.py
fphysics/astrophysics/__init__.py
fphysics/astrophysics/cosmology.py
fphysics/astrophysics/galactic.py
fphysics/astrophysics/planetary.py
fphysics/astrophysics/stellar.py
fphysics/biophysics/__init__.py
fphysics/biophysics/biomechanics.py
fphysics/biophysics/diffusion.py
fphysics/biophysics/membrane.py
fphysics/biophysics/neuroscience.py
fphysics/computational/__init__.py
fphysics/computational/finite_elements.py
fphysics/computational/monte_carlo.py
fphysics/computational/numerical_methods.py
fphysics/computational/optimization.py
fphysics/data/__init__.py
fphysics/data/materials/__init__.py
fphysics/data/materials/materials.py
fphysics/data/spectroscopic data/__init__.py
fphysics/data/spectroscopic data/spectra.py
fphysics/electromagnetism/__init__.py
fphysics/electromagnetism/circuits.py
fphysics/electromagnetism/electrostatics.py
fphysics/electromagnetism/magnetostatics.py
fphysics/electromagnetism/maxwell.py
fphysics/electromagnetism/optics.py
fphysics/electromagnetism/waves.py
fphysics/examples/__init__.py
fphysics/examples/mechanics_examples.py
fphysics/examples/quantum_examples.py
fphysics/examples/thermodynamics_examples.py
fphysics/examples/visualization_examples.py
fphysics/experimental/__init__.py
fphysics/experimental/data_analysis.py
fphysics/experimental/error_analysis.py
fphysics/experimental/instrumentation.py
fphysics/experimental/measurement.py
fphysics/laws/__init__.py
fphysics/laws/conservation.py
fphysics/laws/electromagnetic.py
fphysics/laws/momentum.py
fphysics/laws/newtons_laws.py
fphysics/laws/work_energy.py
fphysics/mathematical/__init__.py
fphysics/mathematical/complex_analysis.py
fphysics/mathematical/differential_equations.py
fphysics/mathematical/group_theory.py
fphysics-1.0.dist-info/licenses/LICENSE
fphysics-1.0.dist-info/METADATA
fphysics-1.0.dist-info/WHEEL
fphysics-1.0.dist-info/top_level.txt
fphysics-1.0.dist-info/RECORD
