Metadata-Version: 2.4
Name: fphysics
Version: 1.0
Summary: A comprehensive physics library providing constants, equations, and formulas
Home-page: https://github.com/n0sync/fphysics
Author: Shakee
Author-email: n0sync <n0sync.76@gmail.com>
License: MIT
Project-URL: Homepage, https://github.com/n0sync/fphysics
Project-URL: Repository, https://github.com/n0sync/fphysics
Project-URL: Issues, https://github.com/n0sync/fphysics/issues
Keywords: physics,science,constants,equations,mechanics,quantum
Classifier: Development Status :: 4 - Beta
Classifier: Intended Audience :: Science/Research
Classifier: Intended Audience :: Education
Classifier: Topic :: Scientific/Engineering :: Physics
Classifier: License :: OSI Approved :: MIT License
Classifier: Programming Language :: Python :: 3
Classifier: Programming Language :: Python :: 3.8
Classifier: Programming Language :: Python :: 3.9
Classifier: Programming Language :: Python :: 3.10
Classifier: Programming Language :: Python :: 3.11
Classifier: Programming Language :: Python :: 3.12
Classifier: Operating System :: OS Independent
Requires-Python: >=3.8
License-File: LICENSE
Requires-Dist: numpy>=1.19.0
Requires-Dist: scipy>=1.7.0
Requires-Dist: matplotlib>=3.3.0
Provides-Extra: dev
Requires-Dist: pytest>=6.0; extra == "dev"
Requires-Dist: pytest-cov>=2.10; extra == "dev"
Requires-Dist: black>=21.0; extra == "dev"
Requires-Dist: flake8>=3.8; extra == "dev"
Requires-Dist: mypy>=0.812; extra == "dev"
Dynamic: author
Dynamic: home-page
Dynamic: license-file
Dynamic: requires-python
